AUTHORS.md
CODE_OF_CONDUCT.md
LICENSE
LICENSE.md
MANIFEST.in
README.md
setup.py
murenn/__init__.py
murenn/version.py
murenn.egg-info/PKG-INFO
murenn.egg-info/SOURCES.txt
murenn.egg-info/dependency_links.txt
murenn.egg-info/requires.txt
murenn.egg-info/top_level.txt
murenn/dtcwt/lowlevel.py
murenn/dtcwt/nn.py
murenn/dtcwt/transform1d.py
murenn/dtcwt/transform_funcs.py
murenn/dtcwt/utils.py
tests/test_dtcwt.py
tests/test_grad.py
tests/test_lowlevel.py
tests/test_nn.py
tests/test_utils.py