Metadata-Version: 2.1
Name: murenn
Version: 0.3.0
Summary: Multiresolution neural networks
Home-page: https://gitlab.univ-nantes.fr/kymatio/murenn
Author: The Kymatio consortium
License: 3-clause BSD
Keywords: wavelets,deep learning,signal processing,audio,speech,music
Classifier: License :: OSI Approved :: ISC License (ISCL)
Classifier: Programming Language :: Python
Classifier: Development Status :: 3 - Alpha
Classifier: Intended Audience :: Developers
Classifier: Topic :: Multimedia :: Sound/Audio :: Analysis
Classifier: Programming Language :: Python :: 3
Classifier: Programming Language :: Python :: 3.6
Classifier: Programming Language :: Python :: 3.7
Classifier: Programming Language :: Python :: 3.8
License-File: LICENSE
License-File: LICENSE.md
License-File: AUTHORS.md
Requires-Dist: dtcwt>=0.13.0
Requires-Dist: torch>=2.0.0
